PaoxueKuaixueXuexiBaodianZhiyedianpian/README.md
PaoxueKuaixueXuexiBaodianZhiyedianpian/__init__.py
PaoxueKuaixueXuexiBaodianZhiyedianpian/__main__.py
PaoxueKuaixueXuexiBaodianZhiyedianpian/file.epub
PaoxueKuaixueXuexiBaodianZhiyedianpian/index.html
PaoxueKuaixueXuexiBaodianZhiyedianpian/css/__init__.py
PaoxueKuaixueXuexiBaodianZhiyedianpian/css/annotations.css
PaoxueKuaixueXuexiBaodianZhiyedianpian/css/main.css
PaoxueKuaixueXuexiBaodianZhiyedianpian/css/normalize.css
PaoxueKuaixueXuexiBaodianZhiyedianpian/css/popup.css
PaoxueKuaixueXuexiBaodianZhiyedianpian/font/__init__.py
PaoxueKuaixueXuexiBaodianZhiyedianpian/font/fontello.eot
PaoxueKuaixueXuexiBaodianZhiyedianpian/font/fontello.svg
PaoxueKuaixueXuexiBaodianZhiyedianpian/font/fontello.ttf
PaoxueKuaixueXuexiBaodianZhiyedianpian/font/fontello.woff
PaoxueKuaixueXuexiBaodianZhiyedianpian/img/__init__.py
PaoxueKuaixueXuexiBaodianZhiyedianpian/img/annotator-glyph-sprite.png
PaoxueKuaixueXuexiBaodianZhiyedianpian/img/annotator-icon-sprite.png
PaoxueKuaixueXuexiBaodianZhiyedianpian/img/apple-touch-icon.png
PaoxueKuaixueXuexiBaodianZhiyedianpian/img/cancelfullscreen.png
PaoxueKuaixueXuexiBaodianZhiyedianpian/img/close.png
PaoxueKuaixueXuexiBaodianZhiyedianpian/img/fullscreen.png
PaoxueKuaixueXuexiBaodianZhiyedianpian/img/loader.gif
PaoxueKuaixueXuexiBaodianZhiyedianpian/img/menu-icon.png
PaoxueKuaixueXuexiBaodianZhiyedianpian/img/save.png
PaoxueKuaixueXuexiBaodianZhiyedianpian/img/saved.png
PaoxueKuaixueXuexiBaodianZhiyedianpian/img/settings-s.png
PaoxueKuaixueXuexiBaodianZhiyedianpian/img/settings.png
PaoxueKuaixueXuexiBaodianZhiyedianpian/img/star.png
PaoxueKuaixueXuexiBaodianZhiyedianpian/js/__init__.py
PaoxueKuaixueXuexiBaodianZhiyedianpian/js/epub.js
PaoxueKuaixueXuexiBaodianZhiyedianpian/js/epub.min.js
PaoxueKuaixueXuexiBaodianZhiyedianpian/js/epub.min.map
PaoxueKuaixueXuexiBaodianZhiyedianpian/js/hooks.min.js
PaoxueKuaixueXuexiBaodianZhiyedianpian/js/hooks.min.map
paoxue_kuaixue_xuexi_baodian_zhiyedianpian-2022.10.11.0.dist-info/METADATA
paoxue_kuaixue_xuexi_baodian_zhiyedianpian-2022.10.11.0.dist-info/WHEEL
paoxue_kuaixue_xuexi_baodian_zhiyedianpian-2022.10.11.0.dist-info/entry_points.txt
paoxue_kuaixue_xuexi_baodian_zhiyedianpian-2022.10.11.0.dist-info/top_level.txt
paoxue_kuaixue_xuexi_baodian_zhiyedianpian-2022.10.11.0.dist-info/RECORD
